<schemalist gettext-domain="gnome-shell-extensions">
  <schema id="org.gnome.shell.extensions.pomodoro" path="/org/gnome/shell/extensions/pomodoro/">
    <key name="period" type="i">
      <default>25</default>
      <summary>Pomodoro period</summary>
      <description>Time in minutes for a pomodoro</description>
    </key>
    <key name="center-display" type="b">
      <default>false</default>
      <summary>Display informations next to the clock</summary>
      <description>True: Set information at the center, False: Set information in status bar (at top right)</description>
    </key>
  </schema>
</schemalist>